relativedeltastore/__init__.py
relativedeltastore/fields.py
relativedeltastore/forms.py
django_relativedeltastore-0.9.5.dist-info/LICENSE
django_relativedeltastore-0.9.5.dist-info/METADATA
django_relativedeltastore-0.9.5.dist-info/WHEEL
django_relativedeltastore-0.9.5.dist-info/top_level.txt
django_relativedeltastore-0.9.5.dist-info/RECORD
