Metadata-Version: 2.1
Name: django-relativedeltastore
Version: 0.9.5
Summary: Django model field to store relativedelta from python-dateutil
Home-page: https://github.com/anfema/django-ses-sns-tracker
Author: anfema GmbH
Author-email: contact@anfe.ma
License: MIT
Platform: UNKNOWN
Classifier: Framework :: Django :: 2.2
Classifier: Framework :: Django :: 3.1
Classifier: Framework :: Django :: 3.2
Classifier: Programming Language :: Python :: 3
Classifier: Programming Language :: Python :: 3.6
Classifier: Programming Language :: Python :: 3.7
Classifier: Programming Language :: Python :: 3.8
Classifier: Programming Language :: Python :: 3.9
Classifier: License :: OSI Approved :: MIT License
Classifier: Operating System :: OS Independent
Requires-Python: >=3.6
License-File: LICENSE
Requires-Dist: python-dateutil
Requires-Dist: Django (>=2.2)
